tests/__init__.py
tests/download_videos.py
tests/get_all_user_videos.py
tests/get_user_info.py
tikfly/TikflyApi.py
tikfly/__init__.py
tikfly/exceptions/TikflyApiError.py
tikfly/exceptions/__init__.py
tikfly/schemas/ChallengeInfoSchema.py
tikfly/schemas/CommentSchema.py
tikfly/schemas/DownloadSchema.py
tikfly/schemas/EffectInfoSchema.py
tikfly/schemas/MusicInfoSchema.py
tikfly/schemas/PlaceInfoShema.py
tikfly/schemas/PostDetailSchema.py
tikfly/schemas/SearchAccountSchema.py
tikfly/schemas/SearchGeneralSchema.py
tikfly/schemas/SearchLiveSchema.py
tikfly/schemas/SearchVideoSchema.py
tikfly/schemas/UserFollowerSchema.py
tikfly/schemas/UserFollowingSchema.py
tikfly/schemas/UserInfoSchema.py
tikfly/schemas/UserPlaylistSchema.py
tikfly/schemas/UserPostSchema.py
tikfly/schemas/UserStorySchema.py
tikfly/schemas/__init__.py
tikfly-1.1.1.dist-info/licenses/LICENSE
tikfly-1.1.1.dist-info/METADATA
tikfly-1.1.1.dist-info/WHEEL
tikfly-1.1.1.dist-info/top_level.txt
tikfly-1.1.1.dist-info/RECORD
