Metadata-Version: 2.4
Name: tikfly
Version: 1.1.1
Summary: Unofficial TikTok API Wrapped in Python
Home-page: https://github.com/tikfly/tikfly-api-py
Author: Tikfly
Author-email: hello@tikfly.io
License: MIT
Project-URL: Documentation, https://docs.tikfly.io
Project-URL: Source, https://github.com/tikfly/tikfly-api-py
Keywords: tiktok,api,unofficial,python,tikfly
License-File: LICENSE
Requires-Dist: aiohttp<4.0.0,>=3.13.3
Requires-Dist: certifi>=2025.11.12
Dynamic: author
Dynamic: author-email
Dynamic: description
Dynamic: description-content-type
Dynamic: home-page
Dynamic: keywords
Dynamic: license
Dynamic: license-file
Dynamic: project-url
Dynamic: requires-dist
Dynamic: summary
